rbyte/__init__.py
rbyte/config.py
rbyte/dataloader.py
rbyte/dataset.py
rbyte/py.typed
rbyte/types.py
rbyte/io/__init__.py
rbyte/io/tree.py
rbyte/io/_duckdb/__init__.py
rbyte/io/_duckdb/dataframe_builder.py
rbyte/io/_mcap/__init__.py
rbyte/io/_mcap/dataframe_builder.py
rbyte/io/_mcap/tensor_source.py
rbyte/io/_mcap/decoders/__init__.py
rbyte/io/_mcap/decoders/json_decoder_factory.py
rbyte/io/_mcap/decoders/protobuf_decoder_factory.py
rbyte/io/_numpy/__init__.py
rbyte/io/_numpy/tensor_source.py
rbyte/io/dataframe/__init__.py
rbyte/io/dataframe/aligner.py
rbyte/io/dataframe/concater.py
rbyte/io/dataframe/groupby.py
rbyte/io/dataframe/indexer.py
rbyte/io/dataframe/sql.py
rbyte/io/geo/__init__.py
rbyte/io/geo/waypoints.py
rbyte/io/hdf5/__init__.py
rbyte/io/hdf5/dataframe_builder.py
rbyte/io/hdf5/tensor_source.py
rbyte/io/path/__init__.py
rbyte/io/path/dataframe_builder.py
rbyte/io/path/tensor_source.py
rbyte/io/video/__init__.py
rbyte/io/video/dataframe_builder.py
rbyte/io/video/torchcodec_source.py
rbyte/io/yaak/__init__.py
rbyte/io/yaak/metadata/__init__.py
rbyte/io/yaak/metadata/dataframe_builder.py
rbyte/io/yaak/metadata/message_iterator.py
rbyte/io/yaak/proto/__init__.py
rbyte/io/yaak/proto/can_pb2.py
rbyte/io/yaak/proto/can_pb2.pyi
rbyte/io/yaak/proto/sensor_pb2.py
rbyte/io/yaak/proto/sensor_pb2.pyi
rbyte/scripts/__init__.py
rbyte/scripts/benchmark_dataloader.py
rbyte/scripts/visualize.py
rbyte/utils/__init__.py
rbyte/utils/_datetime.py
rbyte/utils/dataframe.py
rbyte/viz/__init__.py
rbyte/viz/loggers/__init__.py
rbyte/viz/loggers/base.py
rbyte/viz/loggers/console_logger.py
rbyte/viz/loggers/rerun_logger.py
rbyte-0.32.0.dist-info/METADATA
rbyte-0.32.0.dist-info/WHEEL
rbyte-0.32.0.dist-info/entry_points.txt
rbyte-0.32.0.dist-info/licenses/LICENSE.txt
rbyte-0.32.0.dist-info/RECORD
